ptcmd/__init__.py
ptcmd/argument.py
ptcmd/command.py
ptcmd/completer.py
ptcmd/core.py
ptcmd/info.py
ptcmd/theme.py
ptcmd/version.py
ptcmd-0.3.0.dist-info/METADATA
ptcmd-0.3.0.dist-info/WHEEL
ptcmd-0.3.0.dist-info/licenses/LICENSE
ptcmd-0.3.0.dist-info/RECORD
