Metadata-Version: 2.4
Name: ptcmd
Version: 0.3.0
Summary: A modern cmd library based on prompt_toolkit
Project-URL: Homepage, https://github.com/Visecy/ptcmd
Project-URL: source_archive, https://github.com/Visecy/ptcmd/archive/db31cbc7c6dc3daa4a377cead0dfbb5c3484aea2.zip
Author-email: Visecy <Visecy@visecy.org>
Maintainer-email: Ovizro <ovizro@visecy.org>
License: Apache 2.0
License-File: LICENSE
Keywords: Python,cmd,interactive,prompt
Classifier: Development Status :: 5 - Production/Stable
Classifier: Environment :: Console
Classifier: License :: OSI Approved :: Apache Software License
Classifier: Operating System :: OS Independent
Classifier: Programming Language :: Python :: 3
Classifier: Programming Language :: Python :: 3 :: Only
Classifier: Programming Language :: Python :: 3.8
Classifier: Programming Language :: Python :: 3.9
Classifier: Programming Language :: Python :: 3.10
Classifier: Programming Language :: Python :: 3.11
Classifier: Programming Language :: Python :: 3.12
Classifier: Programming Language :: Python :: 3.13
Classifier: Topic :: Software Development :: Libraries :: Python Modules
Requires-Python: >=3.8
Requires-Dist: prompt-toolkit>=3.0.0
Requires-Dist: pygments>=2.15.0
Requires-Dist: rich-argparse>=1.6.0
Requires-Dist: rich>=13.0.0
Requires-Dist: typing-extensions>=4.5.0
Provides-Extra: dev
Requires-Dist: build>=1.2.0; extra == 'dev'
Requires-Dist: coverage>=7.2.0; extra == 'dev'
Requires-Dist: pytest-asyncio>=0.20.0; extra == 'dev'
Requires-Dist: pytest>=6.0.0; extra == 'dev'
Requires-Dist: ruff>=0.9.0; extra == 'dev'
Provides-Extra: doc
Requires-Dist: mkdocs-awesome-nav>=3.0.0; extra == 'doc'
Requires-Dist: mkdocs-material>=9.0.0; extra == 'doc'
Requires-Dist: mkdocs-mermaid2-plugin>=1.1.0; extra == 'doc'
Requires-Dist: mkdocs-static-i18n>=1.2.0; extra == 'doc'
Requires-Dist: mkdocs>=1.6.0; extra == 'doc'
Provides-Extra: lint
Requires-Dist: ruff>=0.9.0; extra == 'lint'
